
{
  "metadata": {
    "title": "Sprunki Phase 10 - The Ultimate Music Mixing Game",
    "description": "Discover Sprunki Phase 10, a captivating music-mixing game that offers creative freedom, unique characters, and endless musical possibilities.",
    "keywords": "Sprunki Phase 10, music mixing game, musical composition, music games"
  },
  "hero": {
    "h1": "Sprunki Phase 10",
    "p": "Dive into the world of Sprunki Phase 10 - where creativity meets music. Experiment with musical elements and create your unique compositions."
  },
  "gameFeatures": {
    "title": "Game Features",
    "features": [
      "Creative Freedom: Express yourself musically without advanced skills.",
      "Visual & Audio Appeal: Enjoy vibrant visuals and catchy sounds.",
      "Replay Value: Explore different combinations for new sounds and bonuses.",
      "Unique Characters: Each character produces distinct sounds for endless creativity.",
      "Interactive Bonuses: Unlock special tracks and visuals through experimentation."
    ]
  },
  "gameplayInstructions": {
    "title": "How to Play Sprunki Phase 10",
    "instructions": [
      "Select Characters: Choose from characters with unique sounds.",
      "Mix & Match: Drag and drop to create your own musical track.",
      "Unlock Bonuses: Discover combinations that unlock special animations.",
      "Experiment: Keep exploring new sounds for endless possibilities.",
      "Share Your Creations: Let others enjoy your musical masterpieces."
    ]
  },
  "gameScreenshots": {
    "title": "Game Screenshots"
  },
  "playerReviews": {
    "title": "Player Reviews",
    "submitReviewLabel": "Submit Your Review",
    "nameLabel": "Name",
    "reviewLabel": "Review",
    "submitButtonLabel": "Submit",
    "reviews": [
      {
        "content": "Sprunki Phase 10 is a fantastic music game! It's easy to explore and create amazing tunes.",
        "author": "Alice"
      },
      {
        "content": "I love the creativity it offers. I can experiment with different sounds without needing to be a music expert.",
        "author": "Bob"
      },
      {
        "content": "The visual appeal combined with the catchy sounds makes it an engaging game for all ages.",
        "author": "Chris"
      },
      {
        "content": "Every session offers something new. The replay value is one of the best parts of Sprunki Phase 10.",
        "author": "Dana"
      },
      {
        "content": "Unlocking bonuses is my favorite part. It's so rewarding to see new animations.",
        "author": "Evan"
      },
      {
        "content": "I can't stop playing! The unique characters bring a fresh approach to music games.",
        "author": "Fiona"
      },
      {
        "content": "As a music lover, Sprunki Phase 10 has exceeded my expectations. Highly recommended!",
        "author": "George"
      },
      {
        "content": "Great game! It's perfect for relaxing and discovering new musical combinations.",
        "author": "Hannah"
      }
    ]
  },
  "faq": {
    "title": "Frequently Asked Questions",
    "questions": [
      {
        "question": "What is the objective of Sprunki Phase 10?",
        "answer": "The objective is to creatively mix various musical elements to create unique compositions."
      },
      {
        "question": "Do I need music skills to play?",
        "answer": "No, Sprunki Phase 10 is designed to be accessible to everyone, regardless of musical expertise."
      },
      {
        "question": "Can I share my compositions with friends?",
        "answer": "Yes, you can share your musical creations with friends and family for them to enjoy."
      },
      {
        "question": "Are there in-game purchases?",
        "answer": "Sprunki Phase 10 offers in-game content that can be unlocked through gameplay or optional purchases."
      },
      {
        "question": "What platforms is Sprunki Phase 10 available on?",
        "answer": "Sprunki Phase 10 is available on multiple platforms, including PC, iOS, and Android."
      },
      {
        "question": "How often are new updates released?",
        "answer": "The game receives regular updates, introducing new features and content to enhance the experience."
      }
    ]
  }
}
