{
  "metadata": {
    "title": "Sprunki Ketchup 2.0 - Forbedre din skrekkmusikkopplevelse",
    "description": "Dykk ned i den skumle verdenen av Sprunki Ketchup 2.0, hvor musikkproduksjon blir en foruroligende opplevelse. Oppdag spilleregler, funksjoner og spilleranmeldelser.",
    "keywords": "Sprunki Ketchup 2.0, skrekkmusikkspill, spooky lydbilder, spillefunksjoner, spilleranmeldelser"
  },
  "hero": {
    "h1": "Sprunki Ketchup 2.0",
    "p": "Utforsk de urovekkende riker av Sprunki Ketchup 2.0, der skrekk møter musikk i en spennende spillopplevelse."
  },
  "gameFeatures": {
    "title": "Nøkkelfunksjoner i Sprunki Ketchup 2.0",
    "features": [
      "Intensifiserte skrekkestetikk med truende karakterdesign.",
      "Mørkere lydbilder og uhyggelige sløyfer.",
      "Økt spenning med eksperimentelle musikklag.",
      "Kompleks karakterer og urovekkende bakgrunner.",
      "Del skapingene dine med et samfunn av skrekkentusiaster."
    ]
  },
  "gameplayInstructions": {
    "title": "Slik spiller du Sprunki Ketchup 2.0",
    "instructions": [
      "Velg karakterer: Velg figurer som utstråler uhyggelig sjarm.",
      "Dra og slipp dem på lerretet ditt for å lage skremmende komposisjoner.",
      "Eksperimenter med volum og effekter for å oppnå uhyggelig perfeksjon.",
      "Forbedre lagene dine for å avdekke skjulte elementer av frykt.",
      "Lagre og del skrekkmusikkkomposisjonene dine med venner."
    ]
  },
  "gameScreenshots": {
    "title": "Sprunki Ketchup 2.0 Skjermbilder"
  },
  "playerReviews": {
    "title": "Hva spillere sier om Sprunki Ketchup 2.0",
    "submitReviewLabel": "Send inn din anmeldelse",
    "nameLabel": "Navn",
    "reviewLabel": "Anmeldelse",
    "submitButtonLabel": "Send inn",
    "reviews": [
      {
        "content": "Dette spillet har revolusjonert skrekk i musikk - det er et must for spenningssøkere.",
        "author": "Alex"
      },
      {
        "content": "Jeg har aldri følt meg så på kanten mens jeg lager musikk, spenningen er ekte!",
        "author": "Jamie"
      },
      {
        "content": "Perfekt blanding av musikk og skrekk. Sprunki Ketchup 2.0 holder meg hekta!",
        "author": "Chris"
      },
      {
        "content": "De uhyggelige lydbildene er tankevekkende. Gjør deg klar til å bli skremt.",
        "author": "Taylor"
      },
      {
        "content": "Perfekt for Halloween-fester, spill det høyt og skrem vennene dine!",
        "author": "Casey"
      },
      {
        "content": "Jeg elsker virkelig de creepy vibene og den kreative friheten det gir.",
        "author": "Jordan"
      },
      {
        "content": "Sprunki Ketchup 2.0 er en opplevelse som ingen andre. Anbefales på det sterkeste.",
        "author": "Morgan"
      },
      {
        "content": "Spillets atmosfære er intenst skremmende og perfekt for skrekkfans.",
        "author": "Drew"
      }
    ]
  },
  "faq": {
    "title":"Vanlige spørsmål om Sprunki Ketchup 2.0",
    "questions": [
      {
        "question":"Hva er Sprunki Ketchup 2.0?",
        "answer":"Sprunki Ketchup 2.0 er et skrekk-tema musikkspill som introducerer urovekkende lydbilder og visuelle elementer."
      },
      {
        "question":"Hvordan lager jeg musikk i dette spillet?",
        "answer":"Velg og arranger uhyggelige karakterloops på skjermen for å komponere dine egne skremmende spor."
      },
      {
        "question":"Kan jeg dele musikkrealiseringene mine?",
        "answer":"Ja, du kan lagre og dele komposisjonene dine med andre spillere."
      },
      {
        "question":"Er Sprunki Ketchup 2.0 egnet for barn?",
        "answer":"Det anbefales for voksne på grunn av sine skrekk-elementer."
      },
      {
        "question":"Finnes det mikrotransaksjoner i spillet?",
        "answer":"Sprunki Ketchup 2.0 tilbyr flere funksjoner som kan utvides gjennom mikrotransaksjoner."
      },
      {
        "question":"Hvilke plattformer støtter Sprunki Ketchup 2.0?",
        "answer":"Spillet er tilgjengelig på de fleste store spillplattformer, inkludert PC og konsoller."
      }
    ]
  },
  "gameRecommendations": {
    "title": "Anbefalte spill",
    "games": [
      {
        "image": "link_to_image_1.jpg",
        "title": "Spennende Ekkoer",
        "link": "thrilling_echoes_game_url"
      },
      {
        "image": "link_to_image_2.jpg",
        "title": "Hjemsøkete Harmonier",
        "link": "haunted_harmonics_game_url"
      },
      {
        "image": "link_to_image_3.jpg",
        "title": "Skygge Symfoni",
        "link": "shadow_symphony_game_url"
      }
    ]
  }
}