{
  "metadata": {
    "title": "Sperunky Free: रोमांच की गहराइयों में खोज करें",
    "description": "Sperunky Free की दुनिया में डुबकी लगाएँ, एक रोमांचक एडवेंचर गेम जो आपकी खोज और जीवित रहने की क्षमताओं की चुनौती करता है। अद्वितीय विशेषताओं, गेमप्ले निर्देशों की खोज करें और खिलाड़ियों की समीक्षाएँ पड़ें।",
    "keywords": "Sperunky Free, एडवेंचर गेम, खोज, जीवित रहना, गेम समीक्षाएँ"
  },
  "hero": {
    "h1": "Sperunky Free",
    "p": "Sperunky Free के साथ एक महाकाव्य यात्रा पर निकलें, जहाँ आप खतरनाक गुफाओं में नेविगेट करेंगे, बाधाओं को पार करेंगे, और छिपी खजाने की खोज करेंगे!"
  },
  "gameFeatures": {
    "title": "Sperunky Free की विशेषताएँ",
    "features": [
      "खोजने के लिए विशाल गुफाओं का नेटवर्क",
      "यादृच्छिक स्तरों के साथ गतिशील गेमप्ले",
      "फंदों और दुश्मनों की विविधता",
      "सहकारी गेमप्ले के लिए मल्टीप्लेयर मोड",
      "समृद्ध ग्राफिक्स और संगीन ध्वनि प्रभाव"
    ]
  },
  "gameplayInstructions": {
    "title": "Sperunky Free कैसे खेलें",
    "instructions": [
      "अपनी विशेषता को गुफाओं के माध्यम से चलाने के लिए तीर कुंजियों का उपयोग करें।",
      "बाधाओं से बचने के लिए स्पेसबार दबाएँ।",
      "अपनी स्कोर बढ़ाने के लिए खजाने इकट्ठा करें।",
      "कठिन क्षेत्रों में नेविगेट करने के लिए रस्सियाँ और बम जैसे उपकरणों का उपयोग करें।",
      "मल्टीप्लेयर मोड में दोस्तों के साथ सहयोग करें ताकि जटिल चुनौतियों को सुलझा सकें।"
    ]
  },
  "gameScreenshots": {
    "title": "Sperunky Free गेम स्क्रीनशॉट्स"
  },
  "playerReviews": {
    "title": "Sperunky Free की खिलाड़ियों की समीक्षाएँ",
    "submitReviewLabel": "अपनी समीक्षा सबमिट करें",
    "nameLabel": "आपका नाम",
    "reviewLabel": "आपकी समीक्षा",
    "submitButtonLabel": "सबमिट करें",
    "reviews": [
      {
        "content": "Sperunky Free हर स्तर के साथ नए आश्चर्य के साथ एक रोमांचक अनुभव प्रदान करता है।",
        "author": "GameLover123"
      },
      {
        "content": "ग्राफिक्स सुंदर हैं और यह संगीन गेमप्ले में बहुत कुछ जोड़ते हैं।",
        "author": "PixelExplorer"
      },
      {
        "content": "मैं मल्टीप्लेयर मोड में अपने दोस्तों के साथ खेलना पसंद करता हूँ, यह एक साथ योजना बनाने का एक शानदार तरीका है।",
        "author": "TeamPlayer"
      },
      {
        "content": "चुनौतीपूर्ण फिर भी पुरस्कृत, Sperunky Free आपको बार-बार वापस लाता है।",
        "author": "AdventureSeeker"
      },
      {
        "content": "फंदों की विविधता मुझे सतर्क रखती है, यह कभी भी बोरिंग नहीं होता!",
        "author": "TrapMaster"
      },
      {
        "content": "रोमांच और रणनीति के बीच बेहतरीन संतुलन, दोनों शैलियों के प्रशंसकों के लिए अत्यधिक अनुशंसित।",
        "author": "BalancingAct"
      },
      {
        "content": "इस साल मैंने जो सबसे रोमांचक खेल खेला है, उनमें से एक!",
        "author": "ExcitementJunkie"
      },
      {
        "content": "जो कोई भी एडवेंचर और खोज गेम पसंद करता है, उसके लिए इसे खेलना अनिवार्य है।",
        "author": "ExplorerAtHeart"
      }
    ]
  },
  "faq": {
    "title": "अक्सर पूछे जाने वाले प्रश्न: Sperunky Free",
    "questions": [
      {
        "question": "Sperunky Free किन प्लेटफार्मों पर उपलब्ध है?",
        "answer": "Sperunky Free PC, Mac और विभिन्न गेमिंग कंसोल पर उपलब्ध है।"
      },
      {
        "question": "क्या मैं अपने दोस्तों के साथ Sperunky Free खेल सकता हूँ?",
        "answer": "हाँ, Sperunky Free में दोस्तों के साथ सहकारी खेल के लिए एक मल्टीप्लेयर मोड है।"
      },
      {
        "question": "क्या खेल में विभिन्न कठिनाई स्तर हैं?",
        "answer": "हाँ, आप अपनी कौशल स्तर के अनुसार कई कठिनाई स्तरों में से चुन सकते हैं।"
      },
      {
        "question": "क्या खेल खेलने के लिए मुझे इंटरनेट कनेक्शन की जरूरत है?",
        "answer": "मल्टीप्लेयर मोड के लिए इंटरनेट कनेक्शन की आवश्यकता होती है, लेकिन एकल खिलाड़ी के लिए नहीं।"
      },
      {
        "question": "क्या मेरी प्रगति को सहेजने का कोई तरीका है?",
        "answer": "हाँ, Sperunky Free आपकी प्रगति को सुरक्षित करने और बाद में जारी रखने की अनुमति देता है।"
      },
      {
        "question": "क्या खेल में माइक्रोट्रांजैक्शन हैं?",
        "answer": "नहीं, Sperunky Free में कोई माइक्रोट्रांजैक्शन शामिल नहीं हैं।"
      }
    ]
  }
}