{
  "metadata": {
    "title": "Sprunki OWAKCX Mod - একটি ভবিষ্যতনির্ভর সঙ্গীত অভিজ্ঞতা",
    "description": "Sprunki OWAKCX Mod অনুসন্ধান করুন, যেখানে উদ্ভাবনী সাউন্ড প্যালেট এবং দৃষ্টিনন্দন ভিজ্যুয়ালগুলো সঙ্গীত তৈরির নতুন চেহারা প্রতিষ্ঠা করে। গেমটির বৈশিষ্ট্য, বিধি এবং খেলোয়াড়ের পর্যালোচনা আবিষ্কার করুন।",
    "keywords": "Sprunki OWAKCX, সঙ্গীত মড, পরীক্ষামূলক সাউন্ড, উদ্ভাবনী গেমপ্লে, Sprunki বৈশিষ্ট্য"
  },
  "hero": {
    "h1": "Sprunki OWAKCX",
    "p": "Sprunki OWAKCX Mod-এর ভবিষ্যতনির্ভর শব্দ এবং আধুনিক ভিজ্যুয়ালের অনন্য মিশ্রণ দিয়ে আপনার সঙ্গীত সৃষ্টিশীলতাকে মুক্ত করুন।"
  },
  "gameFeatures": {
    "title": "Sprunki OWAKCX Mod এর বৈশিষ্ট্য",
    "features": [
      "উদ্ভাবনী সাউন্ড প্যালেট: ঐতিহ্যবাহী বিট এবং ভবিষ্যতনির্ভর সুরের একটি মিশ্রণ অনুভব করুন।",
      "দৃষ্টিনন্দন ভিজ্যুয়াল: চরিত্র এবং পটভূমিতে সাহসী রঙ এবং অ্যানিমেশন প্রদর্শিত হয়।",
      "সীমাহীন পরীক্ষামূলকতা: অস্বাভাবিক সাউন্ড কম্বিনেশনকে উৎসাহিত করুন।",
      "ডাইনামিক চরিত্র: প্রতিটি চরিত্রে আলাদা, khámparորգ-loop উপলব্ধ।",
      "কাটিং-এজ নিকটবর্তীতা: আধুনিক ডিজাইন যা সৃষ্টির সীমানা এগিয়ে নিয়ে যায়।"
    ]
  },
  "gameplayInstructions": {
    "title": "কীভাবে Sprunki OWAKCX Mod খেলবেন",
    "instructions": [
      "চরিত্র নির্বাচন করুন: অনন্য লুপ নিয়ে চরিত্র নির্বাচন করুন।",
      "ড্র্যাগ এবং ড্রপ: পরিচিত জেনারকে অতিক্রম করার জন্য সাউন্ড স্তরযুক্ত করুন।",
      "আপনার মিক্স পরিশোধন করুন: ভলিউম এবং ইফেক্ট যোগ করুন।",
      "সংরক্ষণ এবং শেয়ার করুন: আপনার ব্যাপক সৃষ্টিগুলি ভাগ করুন।",
      "নিরন্তর অনুসন্ধান করুন: নতুন সাউন্ডস্কেপের সাথে পরীক্ষামূলকভাবে চালিয়ে যান।"
    ]
  },
  "gameScreenshots": {
    "title": "গেম স্ক্রীনশট"
  },
  "playerReviews": {
    "title": "খেলোয়াড়ের পর্যালোচনা",
    "submitReviewLabel": "আপনার পর্যালোচনা জমা দিন",
    "nameLabel": "নাম",
    "reviewLabel": "পর্যালোচনা",
    "submitButtonLabel": "জমা দিন",
    "reviews": [
      {
        "content": "Sprunki OWAKCX আমার জন্য সঙ্গীত তৈরির একটি নতুন জগত উন্মোচন করেছে। এটি মাথা ঘুরিয়ে দিচ্ছে!",
        "author": "অ্যালিস বি।"
      },
      {
        "content": "ভিজ্যুয়ালগুলো চিত্তাকর্ষক এবং সঙ্গীতের সম্ভাবনাগুলো অসীম। আমি নতুন বিটের সাথে পরীক্ষা করতে ভালোবাসি!",
        "author": "জন এস।"
      },
      {
        "content": "আমি আগে কখনো এমন কিছু খেলিনি। এটি একাধিকভাবে চ্যালেঞ্জিং এবং পুরস্কৃত।",
        "author": "এলি টি।"
      },
      {
        "content": "সঙ্গীত গেমগুলির উপর একটি অনন্য মোড়। শব্দ এবং ভিজ্যুয়ালের সমন্বয় আকর্ষক।",
        "author": "নাটালি আর।"
      },
      {
        "content": "এই মডের সাথে সঙ্গীত তৈরি করা আসক্তিকর। আমি নতুন সংমিশ্রণের চেষ্টা করতে ফিরে আসি।",
        "author": "রায়ান পি।"
      },
      {
        "content": "চমৎকার মড! এটি সৃষ্টিশীল সঙ্গীত তৈরিতে সীমানা অতিক্রম করে।",
        "author": "মেগান এল।"
      },
      {
        "content": "Sprunki OWAKCX এর নমনীয়তা এবং সৃষ্টিশীলতা এটি আমাকে সঙ্গীত পরীক্ষার জন্য ধারাবাহিকভাবে তৈরি করেছে।",
        "author": "অবতার এইচ।"
      },
      {
        "content": "আমি সঙ্গীতের প্রতি আগ্রহী যারা নতুন দিগন্ত আবিষ্কার করতে চায় তাদের জন্য এই মডটি উচ্চভাবে সুপারিশ করছি।",
        "author": "সোফি জি।"
      }
    ]
  },
  "faq": {
    "title": "সাধারণত জিজ্ঞাসিত প্রশ্নাবলী",
    "questions": [
      {
        "question": "Sprunki OWAKCX কী?",
        "answer": "Sprunki OWAKCX হল একটি মড যা সঙ্গীত তৈরিতে একটি পরীক্ষামূলক এবং উদ্ভাবনী মোড় নিয়ে আসে।"
      },
      {
        "question": "কীভাবে আমি আমার সৃষ্টিগুলি ভাগShare?",
        "answer": "আপনার ট্র্যাক পরিশোধন করার পরে, আপনার কৃতিত্ব অন্যদের প্রদর্শনের জন্য সংরক্ষণ ও ভাগের বৈশিষ্ট্যটি ব্যবহার করুন।"
      },
      {
        "question": "কী কোনও টিউটোরিয়াল উপলব্ধ আছে?",
        "answer": "হ্যাঁ, গেমটিতে পরীক্ষা শুরু করতে সাহায্য করার জন্য টিউটোরিয়াল এবং টিপস অন্তর্ভুক্ত করা হয়েছে।"
      },
      {
        "question": "আমি কি অন্যান্য খেলোয়াড়দের সাথে সহযোগিতা করতে পারি?",
        "answer": "যদিও এটি প্রধানত একটি একক অভিজ্ঞতা, আপনি আপনার কাজ ভাগShare করতে এবং প্রতিক্রিয়ার মাধ্যমে সহযোগিতা করতে পারেন।"
      },
      {
        "question": "Sprunki OWAKCX কী বিনামূল্যে খেলার জন্য?",
        "answer": "হ্যাঁ, এই মডটি বিনামূল্যে, তবে কিছু অতিরিক্ত বৈশিষ্ট্যে খরচ থাকতে পারে।"
      },
      {
        "question": "কোন সিস্টেমগুলো Sprunki OWAKCX সমর্থন করে?",
        "answer": "মডটি বেশিরভাগ প্রধান অপারেটিং সিস্টেমের জন্য উপলব্ধ, যার মধ্যে Windows এবং MacOS অন্তর্ভুক্ত।"
      }
    ]
  }
}