{
  "metadata": {
    "title": "蜜糖換裝：終極可愛換裝遊戲",
    "description": "在《蜜糖換裝》中發掘樂趣和創意，這是一款令人愉快的換裝遊戲，主角是一位可愛的男孩！直接在你的電腦上遊玩，享受最佳體驗。",
    "keywords": "蜜糖換裝, 換裝遊戲, 可愛遊戲, 線上換裝, 手機換裝, 手繪圖形"
  },
  "hero": {
    "h1": "蜜糖換裝",
    "p": "在《蜜糖換裝》這款可愛與趣味交融的終極換裝遊戲中，盡情展現你的創意和風格！"
  },
  "gameFeatures": {
    "title": "蜜糖換裝的特色",
    "features": [
      "可愛且獨特的女性男孩角色",
      "迷人的手繪圖形，具有MC Paint美學",
      "一個擁有超過100件時尚服裝的大型衣櫃",
      "包含各種泳裝，適合多樣化的造型",
      "定期更新以確保新內容和改進"
    ]
  },
  "gameplayInstructions": {
    "title": "如何玩蜜糖換裝",
    "instructions": [
      "從豐富的衣櫃中選擇你最喜愛的服裝。",
      "拖放物品為可愛的男孩角色換裝。",
      "使用滑鼠在電腦上精確控制，以獲得最佳體驗。",
      "在評論區分享你獨特的服裝創作。",
      "享受無文字的手繪介面，帶來流暢的遊玩體驗。"
    ]
  },
  "gameScreenshots": {
    "title": "遊戲截圖"
  },
  "playerReviews": {
    "title": "玩家評價",
    "submitReviewLabel": "提交你的評價",
    "nameLabel": "你的名字",
    "reviewLabel": "你的評價",
    "submitButtonLabel": "提交",
    "reviews": [
      {
        "content": "設計服裝超有趣！(對不起我的標籤，我不知道為什麼無法裁剪)",
        "author": "Nova (她/他們)"
      },
      {
        "content": "真的很可愛！",
        "author": "HARUHI.JIROU"
      },
      {
        "content": "神作遊戲",
        "author": "RenKun"
      },
      {
        "content": "他好可愛",
        "author": "T0XI :3"
      },
      {
        "content": "哦對我做得不錯 B)",
        "author": "barfbar"
      },
      {
        "content": "這款遊戲真的太傻了，我愛死它了!!! :3",
        "author": "MuinBrownie!!!"
      },
      {
        "content": "完美",
        "author": "yapunglin"
      },
      {
        "content": "我愛這位完全正常的小家伙！",
        "author": "5ummerr"
      }
    ]
  },
  "faq": {
    "title": "常見問題",
    "questions": [
      {
        "question": "我可以在哪些平台上玩《蜜糖換裝》？",
        "answer": "你可以通過HTML5在網頁瀏覽器上和在Windows系統上玩《蜜糖換裝》。"
      },
      {
        "question": "最新的版本是什麼？",
        "answer": "《蜜糖換裝》的最新版本已於2024年2月更新，可以在線上獲得。"
      },
      {
        "question": "有可下載的遊戲版本嗎？",
        "answer": "是的，有可下載的版本，但那是一個較舊的版本是為了存檔而保留的。"
      },
      {
        "question": "我可以在手機上玩這個遊戲嗎？",
        "answer": "《蜜糖換裝》支援手機，但在電腦上的體驗會更佳。"
      },
      {
        "question": "這款遊戲的圖形類型是什麼？",
        "answer": "《蜜糖換裝》使用手繪圖形，具有MC Paint的美學風格。"
      },
      {
        "question": "我怎麼能分享我的服裝創作？",
        "answer": "你可以在遊戲頁面的評論區中分享你的服裝創作。"
      }
    ]
  }
}