
{
  "metadata": {
    "title": "Sprunki - An Entertaining Adventure Game | Play Now",
    "description": "Join the exciting world of Sprunki! Discover the rules, features, and reviews of this captivating adventure game. Play Sprunki now and embark on an epic journey.",
    "keywords": "Sprunki, Sprunki game, adventure game, play Sprunki, Sprunki features, game rules"
  },
  "hero": {
    "h1": "Sprunki",
    "p": "Dive into the thrilling adventure of Sprunki, where every character embarks on an epic journey. Join thousands of players in experiencing the captivating world of Sprunki."
  },
  "gameFeatures": {
    "title": "Sprunki Game Features",
    "features": [
      "Immersive storylines with captivating characters.",
      "Stunning graphics that bring the world of Sprunki to life.",
      "Interactive gameplay that challenges your skills.",
      "Multiplayer modes that allow you to team up with friends.",
      "Regular updates and new content for endless fun."
    ]
  },
  "gameplayInstructions": {
    "title": "How to Play Sprunki",
    "instructions": [
      "Download the Sprunki app from the official website or app store.",
      "Create your character and customize its appearance.",
      "Navigate through levels by using the arrow keys or touchscreen.",
      "Complete quests to gain rewards and advance in the game.",
      "Team up with other players to tackle challenging missions."
    ]
  },
  "gameScreenshots": {
    "title": "Explore the World of Sprunki"
  },
  "playerReviews": {
    "title": "Player Reviews",
    "submitReviewLabel": "Submit Your Review",
    "nameLabel": "Your Name",
    "reviewLabel": "Your Review",
    "submitButtonLabel": "Submit",
    "reviews": [
      {
        "content": "Sprunki is the most fun I've had in a long time! The characters and stories are so engaging.",
        "author": "JaneD"
      },
      {
        "content": "A fantastic game with gorgeous graphics and addictive gameplay!",
        "author": "GameFanatic89"
      },
      {
        "content": "I love the multiplayer mode, playing with friends is a blast!",
        "author": "FriendGamer"
      },
      {
        "content": "Sprunki keeps getting better with every update. Highly recommend!",
        "author": "UpdateLover"
      },
      {
        "content": "The challenges are perfect for a solo gaming session or fun with friends.",
        "author": "SoloPlayer"
      },
      {
        "content": "Great game for both kids and adults. Everyone in my family loves it!",
        "author": "FamilyGamer"
      },
      {
        "content": "Unique characters and creative quests make Sprunki stand out.",
        "author": "QuestMaster"
      },
      {
        "content": "I've been playing Sprunki for months. Engaging and never gets old!",
        "author": "LongTermPlayer"
      }
    ]
  },
  "faq": {
    "title":"Frequently Asked Questions",
    "questions": [
      {
        "question":"Where can I download Sprunki?",
        "answer":"Sprunki can be downloaded from the official website or through major app stores."
      },
      {
        "question":"Is Sprunki available for all devices?",
        "answer":"Yes, Sprunki is available on PC, iOS, and Android devices."
      },
      {
        "question":"Do I need an internet connection to play Sprunki?",
        "answer":"An internet connection is required for multiplayer features, but you can play offline solo missions."
      },
      {
        "question":"Are there any in-game purchases?",
        "answer":"Yes, Sprunki offers optional in-game purchases for character customization and new content."
      },
      {
        "question":"How often is new content released?",
        "answer":"New content and updates are released regularly to keep the game fresh and exciting."
      },
      {
        "question":"Can I play Sprunki with friends?",
        "answer":"Absolutely! Sprunki offers multiplayer modes to play with friends or other online players."
      }
    ]
  }
}
